stix2matcher/__init__.py
stix2matcher/enums.py
stix2matcher/matcher.py
stix2matcher/test/__init__.py
stix2matcher/test/v20/__init__.py
stix2matcher/test/v20/test_basic_ops.py
stix2matcher/test/v20/test_binary.py
stix2matcher/test/v20/test_comparison_exprs.py
stix2matcher/test/v20/test_complex.py
stix2matcher/test/v20/test_matching_sdos.py
stix2matcher/test/v20/test_multi_sdo.py
stix2matcher/test/v20/test_null.py
stix2matcher/test/v20/test_object_path_quoting.py
stix2matcher/test/v20/test_observation_exprs.py
stix2matcher/test/v20/test_references.py
stix2matcher/test/v20/test_temporal_qualifiers.py
stix2matcher/test/v20/test_timestamps.py
stix2matcher/test/v20/test_unicode_normalization.py
stix2matcher/test/v21/__init__.py
stix2matcher/test/v21/test_basic_ops.py
stix2matcher/test/v21/test_binary.py
stix2matcher/test/v21/test_comparison_exprs.py
stix2matcher/test/v21/test_complex.py
stix2matcher/test/v21/test_matching_sdos.py
stix2matcher/test/v21/test_multi_sdo.py
stix2matcher/test/v21/test_null.py
stix2matcher/test/v21/test_object_path_quoting.py
stix2matcher/test/v21/test_observation_exprs.py
stix2matcher/test/v21/test_references.py
stix2matcher/test/v21/test_temporal_qualifiers.py
stix2matcher/test/v21/test_timestamps.py
stix2matcher/test/v21/test_unicode_normalization.py
stix2_matcher-3.0.0.dist-info/LICENSE
stix2_matcher-3.0.0.dist-info/METADATA
stix2_matcher-3.0.0.dist-info/WHEEL
stix2_matcher-3.0.0.dist-info/entry_points.txt
stix2_matcher-3.0.0.dist-info/top_level.txt
stix2_matcher-3.0.0.dist-info/RECORD
